{"nodes": [{"receive": 82, "OU": 0, "name": "England", "send": 243, "id": 34}, {"receive": 83, "OU": 0, "name": "South Africa", "send": 121, "id": 39}, {"receive": 70, "OU": 0, "name": "Australia", "send": 321, "id": 38}, {"receive": 243, "OU": 0, "name": "Namibia", "send": 14, "id": 58}, {"receive": 131, "OU": 0, "name": "Japan", "send": 68, "id": 49}, {"receive": 53, "OU": 0, "name": "Fiji", "send": 80, "id": 46}, {"receive": 137, "OU": 0, "name": "France", "send": 206, "id": 42}, {"receive": 106, "OU": 0, "name": "USA", "send": 68, "id": 51}, {"receive": 104, "OU": 0, "name": "Samoa", "send": 78, "id": 45}, {"receive": 94, "OU": 0, "name": "New Zealand", "send": 291, "id": 37}, {"receive": 82, "OU": 0, "name": "Ireland", "send": 117, "id": 36}, {"receive": 33, "OU": 0, "name": "Argentina", "send": 132, "id": 40}, {"receive": 147, "OU": 0, "name": "Romania", "send": 48, "id": 52}, {"receive": 116, "OU": 0, "name": "Wales", "send": 108, "id": 33}, {"receive": 119, "OU": 0, "name": "Scotland", "send": 86, "id": 35}, {"receive": 116, "OU": 0, "name": "Georgia", "send": 40, "id": 720}, {"receive": 142, "OU": 0, "name": "Tonga", "send": 34, "id": 47}, {"receive": 183, "OU": 0, "name": "Uruguay", "send": 50, "id": 68}, {"receive": 53, "OU": 0, "name": "Italy", "send": 70, "id": 41}, {"receive": 94, "OU": 0, "name": "Canada", "send": 44, "id": 50}], "links": [{"scoreL": 24, "source": 38, "scoreV": 8, "target": 40, "value": 32}, {"scoreL": 70, "source": 37, "scoreV": 7, "target": 41, "value": 77}, {"scoreL": 45, "source": 36, "scoreV": 17, "target": 52, "value": 62}, {"scoreL": 61, "source": 42, "scoreV": 18, "target": 46, "value": 79}, {"scoreL": 72, "source": 39, "scoreV": 6, "target": 68, "value": 78}, {"scoreL": 41, "source": 33, "scoreV": 10, "target": 50, "value": 51}, {"scoreL": 84, "source": 34, "scoreV": 6, "target": 720, "value": 90}, {"scoreL": 32, "source": 35, "scoreV": 11, "target": 49, "value": 43}, {"scoreL": 67, "source": 40, "scoreV": 14, "target": 58, "value": 81}, {"scoreL": 19, "source": 46, "scoreV": 18, "target": 51, "value": 37}, {"scoreL": 36, "source": 41, "scoreV": 12, "target": 47, "value": 48}, {"scoreL": 60, "source": 45, "scoreV": 13, "target": 68, "value": 73}, {"scoreL": 68, "source": 37, "scoreV": 6, "target": 50, "value": 74}, {"scoreL": 90, "source": 38, "scoreV": 8, "target": 52, "value": 98}, {"scoreL": 51, "source": 42, "scoreV": 29, "target": 49, "value": 80}, {"scoreL": 6, "source": 39, "scoreV": 25, "target": 34, "value": 31}, {"scoreL": 27, "source": 33, "scoreV": 20, "target": 47, "value": 47}, {"scoreL": 9, "source": 720, "scoreV": 46, "target": 45, "value": 55}, {"scoreL": 64, "source": 36, "scoreV": 7, "target": 58, "value": 71}, {"scoreL": 39, "source": 35, "scoreV": 15, "target": 51, "value": 54}, {"scoreL": 19, "source": 41, "scoreV": 14, "target": 50, "value": 33}, {"scoreL": 50, "source": 40, "scoreV": 3, "target": 52, "value": 53}, {"scoreL": 41, "source": 46, "scoreV": 13, "target": 49, "value": 54}, {"scoreL": 91, "source": 37, "scoreV": 7, "target": 47, "value": 98}, {"scoreL": 46, "source": 39, "scoreV": 19, "target": 720, "value": 65}, {"scoreL": 142, "source": 38, "scoreV": 0, "target": 58, "value": 142}, {"scoreL": 15, "source": 41, "scoreV": 27, "target": 33, "value": 42}, {"scoreL": 51, "source": 42, "scoreV": 9, "target": 35, "value": 60}, {"scoreL": 15, "source": 40, "scoreV": 16, "target": 36, "value": 31}, {"scoreL": 35, "source": 34, "scoreV": 22, "target": 45, "value": 57}, {"scoreL": 26, "source": 49, "scoreV": 39, "target": 51, "value": 65}, {"scoreL": 12, "source": 720, "scoreV": 24, "target": 68, "value": 36}, {"scoreL": 24, "source": 50, "scoreV": 7, "target": 47, "value": 31}, {"scoreL": 7, "source": 58, "scoreV": 37, "target": 52, "value": 44}, {"scoreL": 41, "source": 42, "scoreV": 14, "target": 51, "value": 55}, {"scoreL": 22, "source": 35, "scoreV": 20, "target": 46, "value": 42}, {"scoreL": 60, "source": 39, "scoreV": 10, "target": 45, "value": 70}, {"scoreL": 17, "source": 38, "scoreV": 16, "target": 36, "value": 33}, {"scoreL": 111, "source": 34, "scoreV": 13, "target": 68, "value": 124}, {"scoreL": 53, "source": 37, "scoreV": 37, "target": 33, "value": 90}, {"scoreL": 29, "source": 37, "scoreV": 9, "target": 39, "value": 38}, {"scoreL": 33, "source": 38, "scoreV": 16, "target": 35, "value": 49}, {"scoreL": 43, "source": 42, "scoreV": 21, "target": 36, "value": 64}, {"scoreL": 28, "source": 34, "scoreV": 17, "target": 33, "value": 45}, {"scoreL": 10, "source": 37, "scoreV": 22, "target": 38, "value": 32}, {"scoreL": 7, "source": 42, "scoreV": 24, "target": 34, "value": 31}, {"scoreL": 13, "source": 42, "scoreV": 40, "target": 37, "value": 53}, {"scoreL": 17, "source": 38, "scoreV": 20, "target": 34, "value": 37}]}